[
{ "url": "img/matter-m/matter-m-1.webp" },
{ "url": "img/matter-m/matter-m-2.webp" },
{ "url": "img/matter-m/matter-m-3.webp" },
{ "url": "img/matter-m/matter-m-4.webp" },
{ "url": "img/matter-m/matter-m-5.webp" },
{ "url": "img/matter-m/matter-m-6.webp" },
{ "url": "img/matter-m/matter-m-7.webp" },
{ "url": "img/matter-m/matter-m-8.webp" },
{ "url": "img/matter-m/matter-m-9.webp" },
{ "url": "img/matter-m/matter-m-10.webp" },
{ "url": "img/matter-m/matter-m-11.webp" },
{ "url": "img/matter-m/matter-m-12.webp" },
{ "url": "img/matter-m/matter-m-13.webp" },
{ "url": "img/matter-m/matter-m-14.webp" },
{ "url": "img/matter-m/matter-m-15.webp" },
{ "url": "img/matter-m/matter-m-16.webp" },
{ "url": "img/matter-m/matter-m-17.webp" },
{ "url": "img/matter-m/matter-m-18.webp" },
{ "url": "img/matter-m/matter-m-19.webp" },
{ "url": "img/matter-m/matter-m-20.webp" },
{ "url": "img/matter-m/matter-m-21.webp" },
{ "url": "img/matter-m/matter-m-22.webp" },
{ "url": "img/matter-m/matter-m-23.webp" },
{ "url": "img/matter-m/matter-m-24.webp" },
{ "url": "img/matter-m/matter-m-25.webp" },
{ "url": "img/matter-m/matter-m-26.webp" },
{ "url": "img/matter-m/matter-m-27.webp" },
{ "url": "img/matter-m/matter-m-28.webp" },
{ "url": "img/matter-m/matter-m-29.webp" },
{ "url": "img/matter-m/matter-m-30.webp" },
{ "url": "img/matter-m/matter-m-31.webp" },
{ "url": "img/matter-m/matter-m-32.webp" },
{ "url": "img/matter-m/matter-m-33.webp" },
{ "url": "img/matter-m/matter-m-34.webp" },
{ "url": "img/matter-m/matter-m-35.webp" },
{ "url": "img/matter-m/matter-m-36.webp" },
{ "url": "img/matter-m/matter-m-37.webp" },
{ "url": "img/matter-m/matter-m-38.webp" },
{ "url": "img/matter-m/matter-m-39.webp" },
{ "url": "img/matter-m/matter-m-40.webp" },
{ "url": "img/matter-m/matter-m-41.webp" },
{ "url": "img/matter-m/matter-m-42.webp" },
{ "url": "img/matter-m/matter-m-43.webp" },
{ "url": "img/matter-m/matter-m-44.webp" },
{ "url": "img/matter-m/matter-m-45.webp" },
{ "url": "img/matter-m/matter-m-46.webp" },
{ "url": "img/matter-m/matter-m-47.webp" },
{ "url": "img/matter-m/matter-m-48.webp" },
{ "url": "img/matter-m/matter-m-49.webp" },
{ "url": "img/matter-m/matter-m-50.webp" },
{ "url": "img/matter-m/matter-m-51.webp" },
{ "url": "img/matter-m/matter-m-52.webp" },
{ "url": "img/matter-m/matter-m-53.webp" },
{ "url": "img/matter-m/matter-m-54.webp" },
{ "url": "img/matter-m/matter-m-55.webp" },
{ "url": "img/matter-m/matter-m-56.webp" },
{ "url": "img/matter-m/matter-m-57.webp" },
{ "url": "img/matter-m/matter-m-58.webp" },
{ "url": "img/matter-m/matter-m-59.webp" },
{ "url": "img/matter-m/matter-m-60.webp" },
{ "url": "img/matter-m/matter-m-61.webp" },
{ "url": "img/matter-m/matter-m-62.webp" },
{ "url": "img/matter-m/matter-m-63.webp" },
{ "url": "img/matter-m/matter-m-64.webp" },
{ "url": "img/matter-m/matter-m-65.webp" },
{ "url": "img/matter-m/matter-m-66.webp" },
{ "url": "img/matter-m/matter-m-67.webp" },
{ "url": "img/matter-m/matter-m-68.webp" },
{ "url": "img/matter-m/matter-m-69.webp" },
{ "url": "img/matter-m/matter-m-70.webp" },
{ "url": "img/matter-m/matter-m-71.webp" },
{ "url": "img/matter-m/matter-m-72.webp" },
{ "url": "img/matter-m/matter-m-73.webp" },
{ "url": "img/matter-m/matter-m-74.webp" },
{ "url": "img/matter-m/matter-m-75.webp" },
{ "url": "img/matter-m/matter-m-76.webp" },
{ "url": "img/matter-m/matter-m-77.webp" },
{ "url": "img/matter-m/matter-m-78.webp" },
{ "url": "img/matter-m/matter-m-79.webp" },
{ "url": "img/matter-m/matter-m-80.webp" },
{ "url": "img/matter-m/matter-m-81.webp" },
{ "url": "img/matter-m/matter-m-82.webp" },
{ "url": "img/matter-m/matter-m-83.webp" },
{ "url": "img/matter-m/matter-m-84.webp" }

]